awe/__init__.py
awe/api.py
awe/api_client.py
awe/chart.py
awe/cli.py
awe/custom.py
awe/decorators.py
awe/element_updater.py
awe/encoding.py
awe/export.py
awe/messages.py
awe/page.py
awe/parser.py
awe/registry.py
awe/variables.py
awe/view.py
awe/webserver.py
awe/websocket.py
awe/resources/VERSION
awe/resources/__init__.py
awe/resources/client/awe/build/asset-manifest.json
awe/resources/client/awe/build/favicon.ico
awe/resources/client/awe/build/index.html
awe/resources/client/awe/build/precache-manifest.db99c6a20fa95dacbd460698f8bd10c6.js
awe/resources/client/awe/build/service-worker.js
awe/resources/client/awe/build/static/css/1.4e2c2c33.chunk.css
awe/resources/client/awe/build/static/css/main.a919138d.chunk.css
awe/resources/client/awe/build/static/js/1.402fe324.chunk.js
awe/resources/client/awe/build/static/js/main.2b50584a.chunk.js
awe/resources/client/awe/build/static/js/runtime~main.22d3d44b.js
awe-0.38.1.dist-info/LICENSE
awe-0.38.1.dist-info/METADATA
awe-0.38.1.dist-info/WHEEL
awe-0.38.1.dist-info/entry_points.txt
awe-0.38.1.dist-info/top_level.txt
awe-0.38.1.dist-info/RECORD
