Metadata-Version: 2.1
Name: awe
Version: 0.38.1
Summary: Dynamic web based reports/dashboards in python
Home-page: https://github.com/dankilman/awe
Author: Dan Kilman
Author-email: UNKNOWN
License: MIT License
Platform: UNKNOWN
Requires-Dist: six
Requires-Dist: bottle
Requires-Dist: autobahn[twisted]
Requires-Dist: twisted
Requires-Dist: service-identity
Requires-Dist: pyyaml
Requires-Dist: txaio
Requires-Dist: pydash
Requires-Dist: requests
Requires-Dist: click
Requires-Dist: typing ; python_version < "3.7"
